LICENSE
MANIFEST.in
README.rst
setup.py
flask_manager/__init__.py
flask_manager/components.py
flask_manager/controller.py
flask_manager/crud.py
flask_manager/rules.py
flask_manager/utils.py
flask_manager/views.py
flask_manager.egg-info/PKG-INFO
flask_manager.egg-info/SOURCES.txt
flask_manager.egg-info/dependency_links.txt
flask_manager.egg-info/not-zip-safe
flask_manager.egg-info/requires.txt
flask_manager.egg-info/top_level.txt
flask_manager/ext/__init__.py
flask_manager/ext/restricted.py
flask_manager/ext/sqlalchemy/__init__.py
flask_manager/ext/sqlalchemy/controller.py
flask_manager/ext/sqlalchemy/crud.py
flask_manager/ext/sqlalchemy/filters.py
flask_manager/static/bootstrap/css/bootstrap-theme.css
flask_manager/static/bootstrap/css/bootstrap-theme.css.map
flask_manager/static/bootstrap/css/bootstrap-theme.min.css
flask_manager/static/bootstrap/css/bootstrap.css
flask_manager/static/bootstrap/css/bootstrap.css.map
flask_manager/static/bootstrap/css/bootstrap.min.css
flask_manager/static/bootstrap/css/custom.css
flask_manager/static/bootstrap/css/select2.min.css
flask_manager/static/bootstrap/fonts/glyphicons-halflings-regular.eot
flask_manager/static/bootstrap/fonts/glyphicons-halflings-regular.svg
flask_manager/static/bootstrap/fonts/glyphicons-halflings-regular.ttf
flask_manager/static/bootstrap/fonts/glyphicons-halflings-regular.woff
flask_manager/static/bootstrap/fonts/glyphicons-halflings-regular.woff2
flask_manager/static/bootstrap/js/bootstrap.js
flask_manager/static/bootstrap/js/bootstrap.min.js
flask_manager/static/bootstrap/js/jquery-2.1.4.js
flask_manager/static/bootstrap/js/jquery-2.1.4.min.js
flask_manager/static/bootstrap/js/jquery-2.1.4.min.map
flask_manager/static/bootstrap/js/jsoneditor.js
flask_manager/static/bootstrap/js/jsoneditor_install.js
flask_manager/static/bootstrap/js/npm.js
flask_manager/static/bootstrap/js/select2.min.js
flask_manager/static/foundation/css/app.css
flask_manager/static/foundation/css/foundation.css
flask_manager/static/foundation/css/foundation.min.css
flask_manager/static/foundation/css/normalize.css
flask_manager/static/foundation/js/app.js
flask_manager/static/foundation/js/foundation.min.js
