Metadata-Version: 1.1
Name: flask-manager
Version: 0.0.1a0
Summary: A CRUD manager for Flask
Home-page: https://github.com/hellupline/flask-crud
Author: Renan Traba
Author-email: hellupline@gmail.com
License: LGPL3
Download-URL: https://github.com/hellupline/flask-manager/tarball/0.0.1
Keywords: flask,crud,sqlalchemy,admin,manager
Platform: UNKNOWN
Classifier: License :: OSI Approved :: GNU Lesser General Public License v3 or later (LGPLv3+)
Classifier: Development Status :: 3 - Alpha
Classifier: Intended Audience :: Developers
Classifier: Environment :: Web Environment
Classifier: Framework :: Flask
Classifier: Operating System :: OS Independent
Classifier: Programming Language :: Python :: 3
Classifier: Programming Language :: Python :: 3.5
Classifier: Topic :: Software Development :: Libraries :: Python Modules
